jwt_validation/__init__.py
jwt_validation/main.py
jwt_validation/validate.py
jwt_validation-0.0.1.dist-info/METADATA
jwt_validation-0.0.1.dist-info/WHEEL
jwt_validation-0.0.1.dist-info/top_level.txt
jwt_validation-0.0.1.dist-info/RECORD
